protomatics/__init__.py
protomatics/analysis.py
protomatics/constants.py
protomatics/data.py
protomatics/helpers.py
protomatics/moments.py
protomatics/plotting.py
protomatics/rendering.py
protomatics-0.8.20.dist-info/LICENSE
protomatics-0.8.20.dist-info/METADATA
protomatics-0.8.20.dist-info/WHEEL
protomatics-0.8.20.dist-info/top_level.txt
protomatics-0.8.20.dist-info/zip-safe
protomatics-0.8.20.dist-info/RECORD
