Metadata-Version: 2.1
Name: protomatics
Version: 0.8.20
Summary: Kinematic analysis of protoplanetary disk data.
Home-page: https://github.com/j-p-terry/protomatics
Author: Jason Terry
Author-email: jason.terry@earth.ox.ac.uk
License: LICENSE.md
Classifier: Development Status :: 4 - Beta
Classifier: Intended Audience :: Developers
Classifier: Intended Audience :: Science/Research
Classifier: License :: OSI Approved :: MIT License
Classifier: Operating System :: OS Independent
Classifier: Programming Language :: Python :: 3
License-File: LICENSE
Requires-Dist: astropy
Requires-Dist: bettermoments
Requires-Dist: colorspacious
Requires-Dist: h5py
Requires-Dist: matplotlib
Requires-Dist: numba
Requires-Dist: numpy
Requires-Dist: pandas
Requires-Dist: pytest
Requires-Dist: sarracen
Requires-Dist: scipy
